pytest_bazel/__init__.py
pytest_bazel/__main__.py
pytest_bazel/main.py
pytest_bazel-0.1.5.dist-info/WHEEL
pytest_bazel-0.1.5.dist-info/METADATA
pytest_bazel-0.1.5.dist-info/entry_points.txt
pytest_bazel-0.1.5.dist-info/LICENSE
pytest_bazel-0.1.5.dist-info/README
pytest_bazel-0.1.5.dist-info/RECORD
