Metadata-Version: 2.1
Name: pytest_bazel
Author: Ignas Anikevicius
Author-email: pypi@anikevicius.lt
Home-page: https://github.com/aignas/pytest-bazel
License: Apache 2.0
Summary: A pytest runner with bazel support
Project-URL: Bug Tracker, https://github.com/aignas/pytest-bazel/issues
Project-URL: Changelog, https://github.com/aignas/pytest-bazel/blob/main/CHANGELOG.md
Project-URL: Documentation, https://github.com/aignas/pytest-bazel
Project-URL: Homepage, https://github.com/aignas/pytest-bazel
Project-URL: Repository, https://github.com/aignas/pytest-bazel.git
Classifier: Development Status :: 4 - Beta
Classifier: Programming Language :: Python
Requires-Dist: pytest
Version: 0.1.5
